tests/__init__.py
tests/async_client_test.py
tests/chat_test.py
tests/chat_v2_test.py
tests/common_test_utils.py
tests/constants.py
tests/database_test.py
tests/history_test.py
tests/multi_tenant_client_test.py
tests/multi_tenant_semantic_context_test.py
tests/push_db_conn.py
tests/query_test.py
tests/semantic_context_test.py
tests/semantic_layer_dump_test.py
tests/test.py
tests/test2.py
tests/user_tests.py
tests/waii_basemodel_test.py
waii_sdk_py/__init__.py
waii_sdk_py/waii_sdk_py.py
waii_sdk_py/access_rules/__init__.py
waii_sdk_py/access_rules/access_rules.py
waii_sdk_py/chart/__init__.py
waii_sdk_py/chart/chart.py
waii_sdk_py/chat/__init__.py
waii_sdk_py/chat/chat.py
waii_sdk_py/common/__init__.py
waii_sdk_py/database/__init__.py
waii_sdk_py/database/database.py
waii_sdk_py/history/__init__.py
waii_sdk_py/history/history.py
waii_sdk_py/my_pydantic/__init__.py
waii_sdk_py/query/__init__.py
waii_sdk_py/query/query.py
waii_sdk_py/semantic_context/__init__.py
waii_sdk_py/semantic_context/semantic_context.py
waii_sdk_py/semantic_layer_dump/__init__.py
waii_sdk_py/semantic_layer_dump/semantic_layer_dump.py
waii_sdk_py/settings/__init__.py
waii_sdk_py/settings/settings.py
waii_sdk_py/user/__init__.py
waii_sdk_py/user/user.py
waii_sdk_py/user/user_static.py
waii_sdk_py/utils/__init__.py
waii_sdk_py/utils/utils.py
waii_sdk_py/waii_http_client/__init__.py
waii_sdk_py/waii_http_client/waii_http_client.py
waii_sdk_py-1.30.0.dist-info/licenses/LICENSE
waii_sdk_py-1.30.0.dist-info/METADATA
waii_sdk_py-1.30.0.dist-info/WHEEL
waii_sdk_py-1.30.0.dist-info/top_level.txt
waii_sdk_py-1.30.0.dist-info/RECORD
