Metadata-Version: 2.4
Name: waii-sdk-py
Version: 1.30.0
Summary: Provides access to the Waii APIs
Home-page: http://www.waii.ai
Author: Waii, Inc.
License: Apache License 2.0
Classifier: Development Status :: 5 - Production/Stable
Classifier: Intended Audience :: Developers
Classifier: License :: OSI Approved :: Apache Software License
Classifier: Programming Language :: Python :: 3
Requires-Python: >=3.9
License-File: LICENSE
Requires-Dist: requests
Dynamic: license-file
